README
setup.py
xmsgsdiff
xmsgsprint
xmsgs/__init__.py
xmsgs_tools.egg-info/PKG-INFO
xmsgs_tools.egg-info/SOURCES.txt
xmsgs_tools.egg-info/dependency_links.txt
xmsgs_tools.egg-info/not-zip-safe
xmsgs_tools.egg-info/top_level.txt