Metadata-Version: 1.0
Name: xmsgs-tools
Version: 0.2.1
Summary: Helper command line tools for parsing large Xilinx ISE FPGA build output logs
Home-page: http://github.com/leaflabs/xmsgs-tools/
Author: Bryan Newbold
Author-email: bnewbold@leaflabs.com
License: MIT
Platform: UNKNOWN
